squareknot/__init__.py
squareknot-0.0.1.dist-info/LICENSE
squareknot-0.0.1.dist-info/METADATA
squareknot-0.0.1.dist-info/WHEEL
squareknot-0.0.1.dist-info/top_level.txt
squareknot-0.0.1.dist-info/RECORD
