Metadata-Version: 2.1
Name: squareknot
Version: 0.0.1
Summary: Connecting the parts of data pipelines
Home-page: https://github.com/cjstoneking/squareknotß
Author: C. J. Stoneking
Author-email: cjstoneking@gmail.com
License: UNKNOWN
Platform: UNKNOWN
Classifier: Programming Language :: Python :: 3
Classifier: License :: OSI Approved :: MIT License
Classifier: Operating System :: OS Independent
Requires-Python: >=3.6
